{"manuellab_vers": [1, 5, 0], "materialproperties": {}, "proportions": {"feet_height_Z": 0.0475, "feet_length": 0.1506, "buttock_depth_Y": 0.2773, "lowerleg_length": 0.2295, "torso_height_Z": 0.3066, "chest_depth_Y": 0.2297, "buttock_height_Z": 0.1207, "upperleg_length": 0.1629, "chest_girth": 0.7919, "neck_height_Z": 0.0065, "upperleg_top_girth": 0.5613, "forearm_length": 0.1646, "waist_girth": 0.9917, "body_height_Z": 1.0, "buttock_girth": 1.0032, "shoulders_width": 0.205, "hands_width": 0.0493, "lowerleg_calf_girth": 0.2766, "neck_girth": 0.3712, "head_height_Z": 0.138, "head_width_X": 0.0871, "head_length": 0.1242, "feet_heel_width": 0.0443, "feet_width": 0.062, "buttock_width_X": 0.3287, "elbow_girth": 0.2592, "upperarm_axillary_girth": 0.3081, "upperarm_length": 0.1685, "upperleg_bottom_girth": 0.3531, "lowerleg_bottom_girth": 0.1654, "wrist_girth": 0.0903, "hands_length": 0.109, "chest_width_X": 0.2215}, "structural": {"Torso_Mass": 1.3, "Neck_Tone": -0.65, "Waist_Size": 0.59, "Stomach_LocalFat": 0.51, "Shoulders_Tone": -0.5, "Arms_UpperarmMass": 1.15, "Hands_Mass": 1.5, "Legs_UpperlegLength": 0.05, "Feet_Size": 0.29, "Neck_Mass": 1.12, "Stomach_Volume": 0.51, "Feet_Mass": 1.24, "Torso_Vshape": 0.26, "Arms_UpperarmLength": 0.44, "Shoulders_Mass": 1.0, "Legs_UpperlegsMass": 1.12, "Legs_LowerlegsMass": 1.3, "Legs_KneeSize": 0.6, "Arms_UpperarmTone": -0.56, "Neck_Length": 0.08, "Pelvis_GluteusTone": -0.5, "Pelvis_SizeX": 0.86, "Pelvis_GluteusMass": 1.21, "Arms_ForearmTone": -0.41, "Cheeks_Tone": -0.5, "Legs_UpperlegsTone": -0.47, "Shoulders_PosZ": 0.35, "Arms_ForearmLength": 0.2, "Head_Size": 0.47, "Hands_Size": 0.32, "Arms_ForearmMass": 1.12, "Wrists_Size": 0.5, "Cheeks_Mass": 1.0, "Hands_FingersLength": 0.11, "Legs_LowerlegsTone": -0.26, "Torso_Tone": -0.56, "Pelvis_SizeY": 0.8}, "metaproperties": {"character_age": 0.0, "last_character_mass": 0.5, "last_character_tone": -1.0, "character_tone": -1.0, "character_mass": 0.5, "last_character_age": 0.0}}