{"manuellab_vers": [1, 5, 0], "materialproperties": {}, "proportions": {"feet_height_Z": 0.0479, "feet_length": 0.1536, "buttock_depth_Y": 0.1892, "lowerleg_length": 0.2184, "torso_height_Z": 0.2716, "chest_depth_Y": 0.178, "buttock_height_Z": 0.1133, "upperleg_length": 0.2, "chest_girth": 0.6354, "neck_height_Z": 0.0262, "upperleg_top_girth": 0.3663, "forearm_length": 0.1732, "waist_girth": 0.6813, "body_height_Z": 1.0, "buttock_girth": 0.6966, "shoulders_width": 0.1937, "hands_width": 0.0475, "lowerleg_calf_girth": 0.2191, "neck_girth": 0.3038, "head_height_Z": 0.1332, "head_width_X": 0.0841, "head_length": 0.1199, "feet_heel_width": 0.0434, "feet_width": 0.0615, "buttock_width_X": 0.2272, "elbow_girth": 0.1987, "upperarm_axillary_girth": 0.2314, "upperarm_length": 0.1643, "upperleg_bottom_girth": 0.2655, "lowerleg_bottom_girth": 0.1376, "wrist_girth": 0.0891, "hands_length": 0.1157, "chest_width_X": 0.1973}, "structural": {"Torso_SizeX": 0.65, "Neck_Tone": -0.56, "Waist_Size": 0.49, "Shoulders_Tone": -0.5, "Arms_ForearmTone": -0.5, "Cheeks_Tone": -0.5, "Legs_UpperlegsTone": -0.5, "Neck_Mass": 0.62, "Torso_Vshape": 0.35, "Torso_SizeY": 0.62, "Wrists_Size": 0.45, "Arms_UpperarmTone": -0.5, "Legs_LowerlegsTone": -0.5, "Pelvis_GluteusTone": -0.5, "Pelvis_GluteusSize": 0.62, "Torso_Tone": -0.62}, "metaproperties": {"character_age": 0.0, "last_character_mass": 0.0, "last_character_tone": -1.0, "character_tone": -1.0, "character_mass": 0.0, "last_character_age": 0.0}}